CHANGELOG.md
COPYING
MANIFEST.in
README.md
VERSION
requirements.txt
setup.py
Oligotyping/__init__.py
Oligotyping/lib/__init__.py
Oligotyping/lib/b6lib.py
Oligotyping/lib/decomposer.py
Oligotyping/lib/entropy.py
Oligotyping/lib/fastalib.py
Oligotyping/lib/oligotyping.py
Oligotyping/lib/shared.py
Oligotyping/lib/topology.py
Oligotyping/utils/__init__.py
Oligotyping/utils/aligner.py
Oligotyping/utils/blast.py
Oligotyping/utils/constants.py
Oligotyping/utils/cosine_similarity.py
Oligotyping/utils/parsers.py
Oligotyping/utils/random_colors.py
Oligotyping/utils/utils.py
Oligotyping/utils/html/__init__.py
Oligotyping/utils/html/error.py
Oligotyping/utils/html/for_decomposition.py
Oligotyping/utils/html/for_oligotyping.py
Oligotyping/utils/html/scripts/README
Oligotyping/utils/html/scripts/g.pie.js
Oligotyping/utils/html/scripts/g.raphael.js
Oligotyping/utils/html/scripts/jquery-1.7.1.js
Oligotyping/utils/html/scripts/morris.LICENSE
Oligotyping/utils/html/scripts/morris.js
Oligotyping/utils/html/scripts/popup.js
Oligotyping/utils/html/scripts/raphael.LICENSE
Oligotyping/utils/html/scripts/raphael.js
Oligotyping/utils/html/static/colorbar.png
Oligotyping/utils/html/static/header_1.png
Oligotyping/utils/html/static/header_2.png
Oligotyping/utils/html/static/missing_image.png
Oligotyping/utils/html/static/style.css
Oligotyping/utils/html/templates/index_for_decomposition.tmpl
Oligotyping/utils/html/templates/index_for_oligo.tmpl
Oligotyping/utils/html/templates/pie_charts_js.tmpl
Oligotyping/utils/html/templates/single_oligo.tmpl
Oligotyping/visualization/__init__.py
Oligotyping/visualization/decomposition_topology.py
Oligotyping/visualization/entropy_distribution_bar.py
Oligotyping/visualization/frequency_curve_and_entropy.py
Oligotyping/visualization/oligotype_distribution_across_samples.py
Oligotyping/visualization/oligotype_distribution_stack_bar.py
Oligotyping/visualization/oligotype_sets_distribution.py
Unittests/_blast.py
Unittests/_decomposition.py
oligotyping.egg-info/PKG-INFO
oligotyping.egg-info/SOURCES.txt
oligotyping.egg-info/dependency_links.txt
oligotyping.egg-info/requires.txt
oligotyping.egg-info/top_level.txt