Metadata-Version: 2.1
Name: oligotyping
Version: 3.2
Summary: The oligotyping and minimum entropy decomposition (MED) pipeline for the analysis of marker gene amplicons
Home-page: http://oligotyping.org
Author: A. Murat Eren
Author-email: a.murat.eren@gmail.com
License: GPLv3+
Classifier: Development Status :: 4 - Beta
Classifier: Environment :: Console
Classifier: Environment :: Web Environment
Classifier: Intended Audience :: Science/Research
Classifier: License :: OSI Approved :: GNU General Public License v3 or later (GPLv3+)
Classifier: Natural Language :: English
Classifier: Operating System :: MacOS
Classifier: Operating System :: POSIX
Classifier: Programming Language :: Python :: 3
Classifier: Topic :: Scientific/Engineering
License-File: COPYING
